Workbook

Sheet Instrucciones
B2: STARTIDEA · CONTROL ECONÓMICO DEL RESTAURANTE
B3: Plantilla para conocer la rentabilidad real del negocio: ventas, costes, márgenes, deuda y punto de equilibrio.
B6: CÓMO USAR ESTA PLANTILLA
B7: 1. Todos los números que ves ahora son DE EJEMPLO. Sustitúyelos por los datos reales del restaurante.
B8: 2. Rellena solo las celdas con fondo amarillo y texto azul. Las celdas en negro son fórmulas: no las toques.
B9: 3. Empieza por VENTAS (un mes de ventas diarias) y GASTOS. Son las hojas más importantes.
B10: 4. Sigue con CARTA (platos, precios y unidades vendidas al mes) y BEBIDAS.
B11: 5. Si conoces los ingredientes y costes de cada plato, rellena ESCANDALLOS: la Carta calculará el margen real por plato.
B12: 6. Completa PERSONAL (sueldos) y DEUDA (préstamos y cuotas).
B13: 7. El DASHBOARD se calcula solo y responde: cuánto ganas, cuánto necesitas facturar para no perder dinero, qué platos dejan dinero y cuáles no.
B15: LEYENDA DE COLORES
B16: • Fondo amarillo + texto azul → dato que debes introducir.
... B30: Plantilla elaborada por Startidea · startidea.es

Sheet Dashboard
B1: 📊 DASHBOARD · RADIOGRAFÍA DEL RESTAURANTE
B2: Se calcula automáticamente a partir del resto de hojas. No escribas aquí salvo en el simulador (amarillo).
B4: VENTAS
B5: Facturación mensual | C5: =Ventas!E34 -> 43320
B6: Cubiertos / clientes al mes | C6: =Ventas!B34 -> 1604
B7: Ticket medio | C7: =IF(C6=0,"",C5/C6) -> 27.007481
B8: Ventas de comida | C8: =Ventas!C34 -> 30500 | D8: =IF(C5=0,"",C8/C5) -> 0.70406279 | E8: % sobre ventas
B9: Ventas de bebida | C9: =Ventas!D34 -> 12820 | D9: =IF(C5=0,"",C9/C5) -> 0.29593721 | E9: objetivo habitual: 25-30%
B11: COSTES
B12: Coste materia prima comida | C12: =Carta!G24 -> 7969.4468 | D12: =IFERROR(C12/Carta!F24,"") -> 0.26119914 | E12: Food cost (obj. 28-32%)
B13: Coste bebidas | C13: =Bebidas!F16 -> 3452 | D13: =IFERROR(C13/Bebidas!E16,"") -> 0.23579235 | E13: Beverage cost (obj. 20-25%)
B14: Coste de personal | C14: =Personal!E12 -> 15774 | D14: =IF(C5=0,"",C14/C5) -> 0.36412742 | E14: obj. 30-35% de ventas
B15: PRIME COST (materia prima + personal) | C15: =C12+C13+C14 -> 27195.447 | D15: =IF(C5=0,"",C15/C5) -> 0.6277804 | E15: obj. < 60-65% de ventas
B16: Gastos operativos | C16: =Gastos!C16 -> 7240 | D16: =IF(C5=0,"",C16/C5) -> 0.16712835
B18: RENTABILIDAD
B19: Costes fijos (personal + gastos fijos) | C19: =C14+Gastos!C17 -> 20384
B20: Margen de contribución | C20: =IF(C5=0,"",1-(C12+C13+Gastos!C18)/C5) -> 0.67563604 | E20: de cada 100 € vendidos, lo que queda para cubrir fijos
B21: PUNTO DE EQUILIBRIO mensual | C21: =IFERROR(C19/C20,"") -> 30170.09 | E21: facturación mínima para no perder dinero
B22: Resultado operativo | C22: =IF(C5=0,"",C5-C12-C13-C14-C16) -> 8884.5532 | D22: =IF(C5=0,"",C22/C5) -> 0.20509125 | E22: margen operativo
B23: Resultado tras cuotas de deuda | C23: =IF(C5=0,"",C22-C25) -> 7044.5532 | E23: caja que queda cada mes tras pagar préstamos
B24: DEUDA
B25: Cuota mensual total de deuda | C25: =Deuda!D11 -> 1840 | D25: =IF(C5=0,"",C25/C5) -> 0.042474608 | E25: % de ventas que se va en cuotas
B26: Deuda total pendiente | C26: =Deuda!B11 -> 69000 | D26: =IF(C22=0,"",C26/(C22*12)) -> 0.64719068 | E26: años de resultado para pagarla
B28: SIMULADOR · ¿Y SI...?
B29: Subo los precios un… | C29: 0.05 | D29: =C5*C29 -> 2166 | E29: € extra al mes (mismo volumen de clientes)
B30: Aumento el ticket medio en… (€) | C30: 2 | D30: =C6*C30 -> 3208 | E30: € extra al mes (postre, vino, sugerencias…)
B31: Compro materia prima un … más barata | C31: 0.08 | D31: =(C12+C13)*C31 -> 913.71575 | E31: € de ahorro al mes (renegociar proveedores)
B33: Plantilla Startidea · los datos actuales son de ejemplo.

Sheet Ventas
A1: VENTAS DIARIAS DEL MES
A3: Día | B3: Cubiertos | C3: Ventas comida (€) | D3: Ventas bebida (€) | E3: Total (€) | F3: Ticket medio (€)
A4: 1 | E4: =IF(AND(C4="",D4=""),"",SUM(C4:D4)) | F4: =IF(OR(B4="",B4=0),"",E4/B4)
A5: 2 | B5: 40 | C5: 760 | D5: 320 | E5: =IF(AND(C5="",D5=""),"",SUM(C5:D5)) -> 1080 | F5: =IF(OR(B5="",B5=0),"",E5/B5) -> 27
A6: 3 | B6: 42 | C6: 800 | D6: 335 | E6: =IF(AND(C6="",D6=""),"",SUM(C6:D6)) -> 1135 | F6: =IF(OR(B6="",B6=0),"",E6/B6) -> 27.02381
A7: 4 | B7: 50 | C7: 950 | D7: 400 | E7: =IF(AND(C7="",D7=""),"",SUM(C7:D7)) -> 1350 | F7: =IF(OR(B7="",B7=0),"",E7/B7) -> 27
A8: 5 | B8: 82 | C8: 1560 | D8: 655 | E8: =IF(AND(C8="",D8=""),"",SUM(C8:D8)) -> 2215 | F8: =IF(OR(B8="",B8=0),"",E8/B8) -> 27.012195
A9: 6 | B9: 105 | C9: 1995 | D9: 840 | E9: =IF(AND(C9="",D9=""),"",SUM(C9:D9)) -> 2835 | F9: =IF(OR(B9="",B9=0),"",E9/B9) -> 27
A10: 7 | B10: 72 | C10: 1370 | D10: 575 | E10: =IF(AND(C10="",D10=""),"",SUM(C10:D10)) -> 1945 | F10: =IF(OR(B10="",B10=0),"",E10/B10) -> 27.013889
A11: 8 | E11: =IF(AND(C11="",D11=""),"",SUM(C11:D11)) | F11: =IF(OR(B11="",B11=0),"",E11/B11)
A12: 9 | B12: 40 | C12: 760 | D12: 320 | E12: =IF(AND(C12="",D12=""),"",SUM(C12:D12)) -> 1080 | F12: =IF(OR(B12="",B12=0),"",E12/B12) -> 27
A13: 10 | B13: 42 | C13: 800 | D13: 335 | E13: =IF(AND(C13="",D13=""),"",SUM(C13:D13)) -> 1135 | F13: =IF(OR(B13="",B13=0),"",E13/B13) -> 27.02381
A14: 11 | B14: 50 | C14: 950 | D14: 400 | E14: =IF(AND(C14="",D14=""),"",SUM(C14:D14)) -> 1350 | F14: =IF(OR(B14="",B14=0),"",E14/B14) -> 27
A15: 12 | B15: 82 | C15: 1560 | D15: 655 | E15: =IF(AND(C15="",D15=""),"",SUM(C15:D15)) -> 2215 | F15: =IF(OR(B15="",B15=0),"",E15/B15) -> 27.012195
A16: 13 | B16: 105 | C16: 1995 | D16: 840 | E16: =IF(AND(C16="",D16=""),"",SUM(C16:D16)) -> 2835 | F16: =IF(OR(B16="",B16=0),"",E16/B16) -> 27
A17: 14 | B17: 72 | C17: 1370 | D17: 575 | E17: =IF(AND(C17="",D17=""),"",SUM(C17:D17)) -> 1945 | F17: =IF(OR(B17="",B17=0),"",E17/B17) -> 27.013889
A18: 15 | E18: =IF(AND(C18="",D18=""),"",SUM(C18:D18)) | F18: =IF(OR(B18="",B18=0),"",E18/B18)
A19: 16 | B19: 40 | C19: 760 | D19: 320 | E19: =IF(AND(C19="",D19=""),"",SUM(C19:D19)) -> 1080 | F19: =IF(OR(B19="",B19=0),"",E19/B19) -> 27
A20: 17 | B20: 42 | C20: 800 | D20: 335 | E20: =IF(AND(C20="",D20=""),"",SUM(C20:D20)) -> 1135 | F20: =IF(OR(B20="",B20=0),"",E20/B20) -> 27.02381
A21: 18 | B21: 50 | C21: 950 | D21: 400 | E21: =IF(AND(C21="",D21=""),"",SUM(C21:D21)) -> 1350 | F21: =IF(OR(B21="",B21=0),"",E21/B21) -> 27
A22: 19 | B22: 82 | C22: 1560 | D22: 655 | E22: =IF(AND(C22="",D22=""),"",SUM(C22:D22)) -> 2215 | F22: =IF(OR(B22="",B22=0),"",E22/B22) -> 27.012195
A23: 20 | B23: 105 | C23: 1995 | D23: 840 | E23: =IF(AND(C23="",D23=""),"",SUM(C23:D23)) -> 2835 | F23: =IF(OR(B23="",B23=0),"",E23/B23) -> 27
A24: 21 | B24: 72 | C24: 1370 | D24: 575 | E24: =IF(AND(C24="",D24=""),"",SUM(C24:D24)) -> 1945 | F24: =IF(OR(B24="",B24=0),"",E24/B24) -> 27.013889
A25: 22 | E25: =IF(AND(C25="",D25=""),"",SUM(C25:D25)) | F25: =IF(OR(B25="",B25=0),"",E25/B25)
A26: 23 | B26: 40 | C26: 760 | D26: 320 | E26: =IF(AND(C26="",D26=""),"",SUM(C26:D26)) -> 1080 | F26: =IF(OR(B26="",B26=0),"",E26/B26) -> 27
A27: 24 | B27: 42 | C27: 800 | D27: 335 | E27: =IF(AND(C27="",D27=""),"",SUM(C27:D27)) -> 1135 | F27: =IF(OR(B27="",B27=0),"",E27/B27) -> 27.02381
A28: 25 | B28: 50 | C28: 950 | D28: 400 | E28: =IF(AND(C28="",D28=""),"",SUM(C28:D28)) -> 1350 | F28: =IF(OR(B28="",B28=0),"",E28/B28) -> 27
A29: 26 | B29: 82 | C29: 1560 | D29: 655 | E29: =IF(AND(C29="",D29=""),"",SUM(C29:D29)) -> 2215 | F29: =IF(OR(B29="",B29=0),"",E29/B29) -> 27.012195
A30: 27 | B30: 105 | C30: 1995 | D30: 840 | E30: =IF(AND(C30="",D30=""),"",SUM(C30:D30)) -> 2835 | F30: =IF(OR(B30="",B30=0),"",E30/B30) -> 27
A31: 28 | B31: 72 | C31: 1370 | D31: 575 | E31: =IF(AND(C31="",D31=""),"",SUM(C31:D31)) -> 1945 | F31: =IF(OR(B31="",B31=0),"",E31/B31) -> 27.013889
A32: 29 | E32: =IF(AND(C32="",D32=""),"",SUM(C32:D32)) | F32: =IF(OR(B32="",B32=0),"",E32/B32)
A33: 30 | B33: 40 | C33: 760 | D33: 320 | E33: =IF(AND(C33="",D33=""),"",SUM(C33:D33)) -> 1080 | F33: =IF(OR(B33="",B33=0),"",E33/B33) -> 27
A34: TOTAL | B34: =SUM(B4:B33) -> 1604 | C34: =SUM(C4:C33) -> 30500 | D34: =SUM(D4:D33) -> 12820 | E34: =SUM(E4:E33) -> 43320 | F34: =IF(B34=0,"",E34/B34) -> 27.007481
A36: Los días sin actividad (cierre) se dejan en blanco. Datos actuales: EJEMPLO.

Sheet Escandallos
A1: ESCANDALLOS · COSTE DE CADA PLATO
A3: Plato | B3: Ingrediente | C3: Cantidad | D3: Unidad | E3: Precio (€/ud) | F3: Merma % | G3: Coste (€)
A4: Croquetas caseras | B4: Jamón ibérico | C4: 0.05 | D4: kg | E4: 18 | F4: 0.05 | G4: =IF(B4="","",C4*E4/(1-F4)) -> 0.94736842
A5: Croquetas caseras | B5: Bechamel (leche, harina, mantequilla) | C5: 0.25 | D5: kg | E5: 2.8 | F5: 0 | G5: =IF(B5="","",C5*E5/(1-F5)) -> 0.7
A6: Croquetas caseras | B6: Pan rallado y huevo | C6: 0.1 | D6: kg | E6: 3 | F6: 0 | G6: =IF(B6="","",C6*E6/(1-F6)) -> 0.3
A7: Croquetas caseras | B7: Aceite de fritura | C7: 0.05 | D7: l | E7: 9 | F7: 0 | G7: =IF(B7="","",C7*E7/(1-F7)) -> 0.45
A8: Ensaladilla rusa | B8: Patata y verduras | C8: 0.3 | D8: kg | E8: 1.6 | F8: 0.1 | G8: =IF(B8="","",C8*E8/(1-F8)) -> 0.53333333
A9: Ensaladilla rusa | B9: Atún y huevo | C9: 0.1 | D9: kg | E9: 8.5 | F9: 0 | G9: =IF(B9="","",C9*E9/(1-F9)) -> 0.85
A10: Ensaladilla rusa | B10: Mayonesa | C10: 0.08 | D10: kg | E10: 3.5 | F10: 0 | G10: =IF(B10="","",C10*E10/(1-F10)) -> 0.28
A11: Pulpo a la brasa | B11: Pulpo cocido | C11: 0.2 | D11: kg | E11: 19.5 | F11: 0.08 | G11: =IF(B11="","",C11*E11/(1-F11)) -> 4.2391304
A12: Pulpo a la brasa | B12: Patata y pimentón | C12: 0.15 | D12: kg | E12: 1.8 | F12: 0.05 | G12: =IF(B12="","",C12*E12/(1-F12)) -> 0.28421053
A13: Pulpo a la brasa | B13: Aceite de oliva virgen | C13: 0.03 | D13: l | E13: 8 | F13: 0 | G13: =IF(B13="","",C13*E13/(1-F13)) -> 0.24
A14: Solomillo ibérico | B14: Solomillo de cerdo ibérico | C14: 0.25 | D14: kg | E14: 16.5 | F14: 0.05 | G14: =IF(B14="","",C14*E14/(1-F14)) -> 4.3421053
A15: Solomillo ibérico | B15: Guarnición y salsa | C15: 0.2 | D15: kg | E15: 3.2 | F15: 0.05 | G15: =IF(B15="","",C15*E15/(1-F15)) -> 0.67368421
... A36: Coulant de chocolate | B36: Helado de vainilla | C36: 0.06 | D36: l | E36: 6.5 | F36: 0 | G36: =IF(B36="","",C36*E36/(1-F36)) -> 0.39
G37: =IF(B37="","",C37*E37/(1-F37))
G38: =IF(B38="","",C38*E38/(1-F38))
G39: =IF(B39="","",C39*E39/(1-F39))
G40: =IF(B40="","",C40*E40/(1-F40))
G41: =IF(B41="","",C41*E41/(1-F41))
G42: =IF(B42="","",C42*E42/(1-F42))
G43: =IF(B43="","",C43*E43/(1-F43))
G44: =IF(B44="","",C44*E44/(1-F44))
G45: =IF(B45="","",C45*E45/(1-F45))
G46: =IF(B46="","",C46*E46/(1-F46))
G47: =IF(B47="","",C47*E47/(1-F47))
G48: =IF(B48="","",C48*E48/(1-F48))
... G63: =IF(B63="","",C63*E63/(1-F63))
A65: Coste = cantidad × precio ÷ (1 − merma). La merma es el % que se pierde al limpiar/cocinar.

Sheet Carta
A1: CARTA · RENTABILIDAD POR PLATO
A3: Plato | B3: Categoría | C3: PVP (€) | D3: Unidades/mes | E3: Coste ración (€) | F3: Ingresos (€) | G3: Coste total (€) | H3: Margen (€) | I3: Margen % | J3: Food cost plato | K3: Clasificación
A4: Croquetas caseras | B4: Entrante | C4: 8.5 | D4: 320 | E4: =IF(A4="","",SUMIF(Escandallos!$A$4:$A$63,A4,Escandallos!$G$4:$G$63)) -> 2.3973684 | F4: =IF(A4="","",C4*D4) -> 2720 | G4: =IF(A4="","",E4*D4) -> 767.15789 | H4: =IF(A4="","",F4-G4) -> 1952.8421 | I4: =IF(OR(A4="",F4=0),"",H4/F4) -> 0.71795666 | J4: =IF(OR(A4="",C4=0),"",E4/C4) -> 0.28204334 | K4: =IF(A4="","",IF(AND(D4>=$D$25,I4>=$I$25),"⭐ Estrella (mantener)",IF(D4>=$D$25,"🐮 Popular con poco margen (subir precio o bajar coste)",IF(I4>=$I$25,"🧩 Rentable poco pedido (promocionar)","🐕 Revisar o retirar")))) -> 🐮 Popular con poco margen (subir precio o bajar coste)
A5: Ensaladilla rusa | B5: Entrante | C5: 7.5 | D5: 260 | E5: =IF(A5="","",SUMIF(Escandallos!$A$4:$A$63,A5,Escandallos!$G$4:$G$63)) -> 1.6633333 | F5: =IF(A5="","",C5*D5) -> 1950 | G5: =IF(A5="","",E5*D5) -> 432.46667 | H5: =IF(A5="","",F5-G5) -> 1517.5333 | I5: =IF(OR(A5="",F5=0),"",H5/F5) -> 0.77822222 | J5: =IF(OR(A5="",C5=0),"",E5/C5) -> 0.22177778 | K5: =IF(A5="","",IF(AND(D5>=$D$25,I5>=$I$25),"⭐ Estrella (mantener)",IF(D5>=$D$25,"🐮 Popular con poco margen (subir precio o bajar coste)",IF(I5>=$I$25,"🧩 Rentable poco pedido (promocionar)","🐕 Revisar o retirar")))) -> ⭐ Estrella (mantener)
A6: Pulpo a la brasa | B6: Entrante | C6: 16.9 | D6: 140 | E6: =IF(A6="","",SUMIF(Escandallos!$A$4:$A$63,A6,Escandallos!$G$4:$G$63)) -> 4.763341 | F6: =IF(A6="","",C6*D6) -> 2366 | G6: =IF(A6="","",E6*D6) -> 666.86773 | H6: =IF(A6="","",F6-G6) -> 1699.1323 | I6: =IF(OR(A6="",F6=0),"",H6/F6) -> 0.71814551 | J6: =IF(OR(A6="",C6=0),"",E6/C6) -> 0.28185449 | K6: =IF(A6="","",IF(AND(D6>=$D$25,I6>=$I$25),"⭐ Estrella (mantener)",IF(D6>=$D$25,"🐮 Popular con poco margen (subir precio o bajar coste)",IF(I6>=$I$25,"🧩 Rentable poco pedido (promocionar)","🐕 Revisar o retirar")))) -> 🐕 Revisar o retirar
A7: Solomillo ibérico | B7: Carne | C7: 18.5 | D7: 210 | E7: =IF(A7="","",SUMIF(Escandallos!$A$4:$A$63,A7,Escandallos!$G$4:$G$63)) -> 5.0157895 | F7: =IF(A7="","",C7*D7) -> 3885 | G7: =IF(A7="","",E7*D7) -> 1053.3158 | H7: =IF(A7="","",F7-G7) -> 2831.6842 | I7: =IF(OR(A7="",F7=0),"",H7/F7) -> 0.72887624 | J7: =IF(OR(A7="",C7=0),"",E7/C7) -> 0.27112376 | K7: =IF(A7="","",IF(AND(D7>=$D$25,I7>=$I$25),"⭐ Estrella (mantener)",IF(D7>=$D$25,"🐮 Popular con poco margen (subir precio o bajar coste)",IF(I7>=$I$25,"🧩 Rentable poco pedido (promocionar)","🐕 Revisar o retirar")))) -> 🐕 Revisar o retirar
A8: Entrecot de ternera | B8: Carne | C8: 21 | D8: 150 | E8: =IF(A8="","",SUMIF(Escandallos!$A$4:$A$63,A8,Escandallos!$G$4:$G$63)) -> 6.721968 | F8: =IF(A8="","",C8*D8) -> 3150 | G8: =IF(A8="","",E8*D8) -> 1008.2952 | H8: =IF(A8="","",F8-G8) -> 2141.7048 | I8: =IF(OR(A8="",F8=0),"",H8/F8) -> 0.67990629 | J8: =IF(OR(A8="",C8=0),"",E8/C8) -> 0.32009371 | K8: =IF(A8="","",IF(AND(D8>=$D$25,I8>=$I$25),"⭐ Estrella (mantener)",IF(D8>=$D$25,"🐮 Popular con poco margen (subir precio o bajar coste)",IF(I8>=$I$25,"🧩 Rentable poco pedido (promocionar)","🐕 Revisar o retirar")))) -> 🐕 Revisar o retirar
A9: Hamburguesa gourmet | B9: Carne | C9: 12.9 | D9: 340 | E9: =IF(A9="","",SUMIF(Escandallos!$A$4:$A$63,A9,Escandallos!$G$4:$G$63)) -> 3.3928866 | F9: =IF(A9="","",C9*D9) -> 4386 | G9: =IF(A9="","",E9*D9) -> 1153.5814 | H9: =IF(A9="","",F9-G9) -> 3232.4186 | I9: =IF(OR(A9="",F9=0),"",H9/F9) -> 0.73698554 | J9: =IF(OR(A9="",C9=0),"",E9/C9) -> 0.26301446 | K9: =IF(A9="","",IF(AND(D9>=$D$25,I9>=$I$25),"⭐ Estrella (mantener)",IF(D9>=$D$25,"🐮 Popular con poco margen (subir precio o bajar coste)",IF(I9>=$I$25,"🧩 Rentable poco pedido (promocionar)","🐕 Revisar o retirar")))) -> 🐮 Popular con poco margen (subir precio o bajar coste)
A10: Lubina a la plancha | B10: Pescado | C10: 17.5 | D10: 120 | E10: =IF(A10="","",SUMIF(Escandallos!$A$4:$A$63,A10,Escandallos!$G$4:$G$63)) -> 6.0219814 | F10: =IF(A10="","",C10*D10) -> 2100 | G10: =IF(A10="","",E10*D10) -> 722.63777 | H10: =IF(A10="","",F10-G10) -> 1377.3622 | I10: =IF(OR(A10="",F10=0),"",H10/F10) -> 0.65588678 | J10: =IF(OR(A10="",C10=0),"",E10/C10) -> 0.34411322 | K10: =IF(A10="","",IF(AND(D10>=$D$25,I10>=$I$25),"⭐ Estrella (mantener)",IF(D10>=$D$25,"🐮 Popular con poco margen (subir precio o bajar coste)",IF(I10>=$I$25,"🧩 Rentable poco pedido (promocionar)","🐕 Revisar o retirar")))) -> 🐕 Revisar o retirar
A11: Bacalao confitado | B11: Pescado | C11: 16 | D11: 90 | E11: =IF(A11="","",SUMIF(Escandallos!$A$4:$A$63,A11,Escandallos!$G$4:$G$63)) -> 4.7666667 | F11: =IF(A11="","",C11*D11) -> 1440 | G11: =IF(A11="","",E11*D11) -> 429 | H11: =IF(A11="","",F11-G11) -> 1011 | I11: =IF(OR(A11="",F11=0),"",H11/F11) -> 0.70208333 | J11: =IF(OR(A11="",C11=0),"",E11/C11) -> 0.29791667 | K11: =IF(A11="","",IF(AND(D11>=$D$25,I11>=$I$25),"⭐ Estrella (mantener)",IF(D11>=$D$25,"🐮 Popular con poco margen (subir precio o bajar coste)",IF(I11>=$I$25,"🧩 Rentable poco pedido (promocionar)","🐕 Revisar o retirar")))) -> 🐕 Revisar o retirar
A12: Paella (ración) | B12: Arroz | C12: 14.5 | D12: 280 | E12: =IF(A12="","",SUMIF(Escandallos!$A$4:$A$63,A12,Escandallos!$G$4:$G$63)) -> 2.866 | F12: =IF(A12="","",C12*D12) -> 4060 | G12: =IF(A12="","",E12*D12) -> 802.48 | H12: =IF(A12="","",F12-G12) -> 3257.52 | I12: =IF(OR(A12="",F12=0),"",H12/F12) -> 0.80234483 | J12: =IF(OR(A12="",C12=0),"",E12/C12) -> 0.19765517 | K12: =IF(A12="","",IF(AND(D12>=$D$25,I12>=$I$25),"⭐ Estrella (mantener)",IF(D12>=$D$25,"🐮 Popular con poco margen (subir precio o bajar coste)",IF(I12>=$I$25,"🧩 Rentable poco pedido (promocionar)","🐕 Revisar o retirar")))) -> ⭐ Estrella (mantener)
A13: Risotto de setas | B13: Arroz | C13: 12 | D13: 110 | E13: =IF(A13="","",SUMIF(Escandallos!$A$4:$A$63,A13,Escandallos!$G$4:$G$63)) -> 2.5231304 | F13: =IF(A13="","",C13*D13) -> 1320 | G13: =IF(A13="","",E13*D13) -> 277.54435 | H13: =IF(A13="","",F13-G13) -> 1042.4557 | I13: =IF(OR(A13="",F13=0),"",H13/F13) -> 0.78973913 | J13: =IF(OR(A13="",C13=0),"",E13/C13) -> 0.21026087 | K13: =IF(A13="","",IF(AND(D13>=$D$25,I13>=$I$25),"⭐ Estrella (mantener)",IF(D13>=$D$25,"🐮 Popular con poco margen (subir precio o bajar coste)",IF(I13>=$I$25,"🧩 Rentable poco pedido (promocionar)","🐕 Revisar o retirar")))) -> 🧩 Rentable poco pedido (promocionar)
A14: Tarta de queso | B14: Postre | C14: 5.9 | D14: 300 | E14: =IF(A14="","",SUMIF(Escandallos!$A$4:$A$63,A14,Escandallos!$G$4:$G$63)) -> 1.065 | F14: =IF(A14="","",C14*D14) -> 1770 | G14: =IF(A14="","",E14*D14) -> 319.5 | H14: =IF(A14="","",F14-G14) -> 1450.5 | I14: =IF(OR(A14="",F14=0),"",H14/F14) -> 0.81949153 | J14: =IF(OR(A14="",C14=0),"",E14/C14) -> 0.18050847 | K14: =IF(A14="","",IF(AND(D14>=$D$25,I14>=$I$25),"⭐ Estrella (mantener)",IF(D14>=$D$25,"🐮 Popular con poco margen (subir precio o bajar coste)",IF(I14>=$I$25,"🧩 Rentable poco pedido (promocionar)","🐕 Revisar o retirar")))) -> ⭐ Estrella (mantener)
A15: Coulant de chocolate | B15: Postre | C15: 6.2 | D15: 220 | E15: =IF(A15="","",SUMIF(Escandallos!$A$4:$A$63,A15,Escandallos!$G$4:$G$63)) -> 1.53 | F15: =IF(A15="","",C15*D15) -> 1364 | G15: =IF(A15="","",E15*D15) -> 336.6 | H15: =IF(A15="","",F15-G15) -> 1027.4 | I15: =IF(OR(A15="",F15=0),"",H15/F15) -> 0.75322581 | J15: =IF(OR(A15="",C15=0),"",E15/C15) -> 0.24677419 | K15: =IF(A15="","",IF(AND(D15>=$D$25,I15>=$I$25),"⭐ Estrella (mantener)",IF(D15>=$D$25,"🐮 Popular con poco margen (subir precio o bajar coste)",IF(I15>=$I$25,"🧩 Rentable poco pedido (promocionar)","🐕 Revisar o retirar")))) -> ⭐ Estrella (mantener)
E16: =IF(A16="","",SUMIF(Escandallos!$A$4:$A$63,A16,Escandallos!$G$4:$G$63)) | F16: =IF(A16="","",C16*D16) | G16: =IF(A16="","",E16*D16) | H16: =IF(A16="","",F16-G16) | I16: =IF(OR(A16="",F16=0),"",H16/F16) | J16: =IF(OR(A16="",C16=0),"",E16/C16) | K16: =IF(A16="","",IF(AND(D16>=$D$25,I16>=$I$25),"⭐ Estrella (mantener)",IF(D16>=$D$25,"🐮 Popular con poco margen (subir precio o bajar coste)",IF(I16>=$I$25,"🧩 Rentable poco pedido (promocionar)","🐕 Revisar o retirar"))))
E17: =IF(A17="","",SUMIF(Escandallos!$A$4:$A$63,A17,Escandallos!$G$4:$G$63)) | F17: =IF(A17="","",C17*D17) | G17: =IF(A17="","",E17*D17) | H17: =IF(A17="","",F17-G17) | I17: =IF(OR(A17="",F17=0),"",H17/F17) | J17: =IF(OR(A17="",C17=0),"",E17/C17) | K17: =IF(A17="","",IF(AND(D17>=$D$25,I17>=$I$25),"⭐ Estrella (mantener)",IF(D17>=$D$25,"🐮 Popular con poco margen (subir precio o bajar coste)",IF(I17>=$I$25,"🧩 Rentable poco pedido (promocionar)","🐕 Revisar o retirar"))))
E18: =IF(A18="","",SUMIF(Escandallos!$A$4:$A$63,A18,Escandallos!$G$4:$G$63)) | F18: =IF(A18="","",C18*D18) | G18: =IF(A18="","",E18*D18) | H18: =IF(A18="","",F18-G18) | I18: =IF(OR(A18="",F18=0),"",H18/F18) | J18: =IF(OR(A18="",C18=0),"",E18/C18) | K18: =IF(A18="","",IF(AND(D18>=$D$25,I18>=$I$25),"⭐ Estrella (mantener)",IF(D18>=$D$25,"🐮 Popular con poco margen (subir precio o bajar coste)",IF(I18>=$I$25,"🧩 Rentable poco pedido (promocionar)","🐕 Revisar o retirar"))))
E19: =IF(A19="","",SUMIF(Escandallos!$A$4:$A$63,A19,Escandallos!$G$4:$G$63)) | F19: =IF(A19="","",C19*D19) | G19: =IF(A19="","",E19*D19) | H19: =IF(A19="","",F19-G19) | I19: =IF(OR(A19="",F19=0),"",H19/F19) | J19: =IF(OR(A19="",C19=0),"",E19/C19) | K19: =IF(A19="","",IF(AND(D19>=$D$25,I19>=$I$25),"⭐ Estrella (mantener)",IF(D19>=$D$25,"🐮 Popular con poco margen (subir precio o bajar coste)",IF(I19>=$I$25,"🧩 Rentable poco pedido (promocionar)","🐕 Revisar o retirar"))))
E20: =IF(A20="","",SUMIF(Escandallos!$A$4:$A$63,A20,Escandallos!$G$4:$G$63)) | F20: =IF(A20="","",C20*D20) | G20: =IF(A20="","",E20*D20) | H20: =IF(A20="","",F20-G20) | I20: =IF(OR(A20="",F20=0),"",H20/F20) | J20: =IF(OR(A20="",C20=0),"",E20/C20) | K20: =IF(A20="","",IF(AND(D20>=$D$25,I20>=$I$25),"⭐ Estrella (mantener)",IF(D20>=$D$25,"🐮 Popular con poco margen (subir precio o bajar coste)",IF(I20>=$I$25,"🧩 Rentable poco pedido (promocionar)","🐕 Revisar o retirar"))))
E21: =IF(A21="","",SUMIF(Escandallos!$A$4:$A$63,A21,Escandallos!$G$4:$G$63)) | F21: =IF(A21="","",C21*D21) | G21: =IF(A21="","",E21*D21) | H21: =IF(A21="","",F21-G21) | I21: =IF(OR(A21="",F21=0),"",H21/F21) | J21: =IF(OR(A21="",C21=0),"",E21/C21) | K21: =IF(A21="","",IF(AND(D21>=$D$25,I21>=$I$25),"⭐ Estrella (mantener)",IF(D21>=$D$25,"🐮 Popular con poco margen (subir precio o bajar coste)",IF(I21>=$I$25,"🧩 Rentable poco pedido (promocionar)","🐕 Revisar o retirar"))))
E22: =IF(A22="","",SUMIF(Escandallos!$A$4:$A$63,A22,Escandallos!$G$4:$G$63)) | F22: =IF(A22="","",C22*D22) | G22: =IF(A22="","",E22*D22) | H22: =IF(A22="","",F22-G22) | I22: =IF(OR(A22="",F22=0),"",H22/F22) | J22: =IF(OR(A22="",C22=0),"",E22/C22) | K22: =IF(A22="","",IF(AND(D22>=$D$25,I22>=$I$25),"⭐ Estrella (mantener)",IF(D22>=$D$25,"🐮 Popular con poco margen (subir precio o bajar coste)",IF(I22>=$I$25,"🧩 Rentable poco pedido (promocionar)","🐕 Revisar o retirar"))))
E23: =IF(A23="","",SUMIF(Escandallos!$A$4:$A$63,A23,Escandallos!$G$4:$G$63)) | F23: =IF(A23="","",C23*D23) | G23: =IF(A23="","",E23*D23) | H23: =IF(A23="","",F23-G23) | I23: =IF(OR(A23="",F23=0),"",H23/F23) | J23: =IF(OR(A23="",C23=0),"",E23/C23) | K23: =IF(A23="","",IF(AND(D23>=$D$25,I23>=$I$25),"⭐ Estrella (mantener)",IF(D23>=$D$25,"🐮 Popular con poco margen (subir precio o bajar coste)",IF(I23>=$I$25,"🧩 Rentable poco pedido (promocionar)","🐕 Revisar o retirar"))))
A24: TOTAL | F24: =SUM(F4:F23) -> 30511 | G24: =SUM(G4:G23) -> 7969.4468 | H24: =SUM(H4:H23) -> 22541.553 | I24: =IF(F24=0,"",H24/F24) -> 0.73880086
A25: Media (para clasificar) | D25: =IFERROR(AVERAGEIF($A$4:$A$23,"<>",$D$4:$D$23),0) -> 211.66667 | I25: =IFERROR(AVERAGEIF($A$4:$A$23,"<>",$I$4:$I$23),0) -> 0.74023865
A27: El coste de ración llega automáticamente desde la hoja Escandallos. Clasificación: ingeniería de menú (popularidad × margen frente a la media).

Sheet Bebidas
A1: BEBIDAS · MARGEN POR PRODUCTO
A3: Bebida | B3: Coste (€/ud) | C3: PVP (€) | D3: Unidades/mes | E3: Ingresos (€) | F3: Coste total (€) | G3: Margen (€) | H3: Margen %
A4: Caña de cerveza | B4: 0.4 | C4: 2.2 | D4: 1600 | E4: =IF(A4="","",C4*D4) -> 3520 | F4: =IF(A4="","",B4*D4) -> 640 | G4: =IF(A4="","",E4-F4) -> 2880 | H4: =IF(OR(A4="",E4=0),"",G4/E4) -> 0.81818182
A5: Copa de vino | B5: 1.1 | C5: 3.5 | D5: 700 | E5: =IF(A5="","",C5*D5) -> 2450 | F5: =IF(A5="","",B5*D5) -> 770 | G5: =IF(A5="","",E5-F5) -> 1680 | H5: =IF(OR(A5="",E5=0),"",G5/E5) -> 0.68571429
A6: Botella de vino | B6: 6.5 | C6: 16 | D6: 120 | E6: =IF(A6="","",C6*D6) -> 1920 | F6: =IF(A6="","",B6*D6) -> 780 | G6: =IF(A6="","",E6-F6) -> 1140 | H6: =IF(OR(A6="",E6=0),"",G6/E6) -> 0.59375
A7: Refresco | B7: 0.45 | C7: 2.5 | D7: 900 | E7: =IF(A7="","",C7*D7) -> 2250 | F7: =IF(A7="","",B7*D7) -> 405 | G7: =IF(A7="","",E7-F7) -> 1845 | H7: =IF(OR(A7="",E7=0),"",G7/E7) -> 0.82
A8: Agua | B8: 0.3 | C8: 1.8 | D8: 800 | E8: =IF(A8="","",C8*D8) -> 1440 | F8: =IF(A8="","",B8*D8) -> 240 | G8: =IF(A8="","",E8-F8) -> 1200 | H8: =IF(OR(A8="",E8=0),"",G8/E8) -> 0.83333333
A9: Café | B9: 0.25 | C9: 1.5 | D9: 1100 | E9: =IF(A9="","",C9*D9) -> 1650 | F9: =IF(A9="","",B9*D9) -> 275 | G9: =IF(A9="","",E9-F9) -> 1375 | H9: =IF(OR(A9="",E9=0),"",G9/E9) -> 0.83333333
A10: Gin-tonic / combinado | B10: 1.8 | C10: 7 | D10: 150 | E10: =IF(A10="","",C10*D10) -> 1050 | F10: =IF(A10="","",B10*D10) -> 270 | G10: =IF(A10="","",E10-F10) -> 780 | H10: =IF(OR(A10="",E10=0),"",G10/E10) -> 0.74285714
A11: Zumo natural | B11: 0.6 | C11: 3 | D11: 120 | E11: =IF(A11="","",C11*D11) -> 360 | F11: =IF(A11="","",B11*D11) -> 72 | G11: =IF(A11="","",E11-F11) -> 288 | H11: =IF(OR(A11="",E11=0),"",G11/E11) -> 0.8
E12: =IF(A12="","",C12*D12) | F12: =IF(A12="","",B12*D12) | G12: =IF(A12="","",E12-F12) | H12: =IF(OR(A12="",E12=0),"",G12/E12)
E13: =IF(A13="","",C13*D13) | F13: =IF(A13="","",B13*D13) | G13: =IF(A13="","",E13-F13) | H13: =IF(OR(A13="",E13=0),"",G13/E13)
E14: =IF(A14="","",C14*D14) | F14: =IF(A14="","",B14*D14) | G14: =IF(A14="","",E14-F14) | H14: =IF(OR(A14="",E14=0),"",G14/E14)
E15: =IF(A15="","",C15*D15) | F15: =IF(A15="","",B15*D15) | G15: =IF(A15="","",E15-F15) | H15: =IF(OR(A15="",E15=0),"",G15/E15)
A16: TOTAL | E16: =SUM(E4:E15) -> 14640 | F16: =SUM(F4:F15) -> 3452 | G16: =SUM(G4:G15) -> 11188 | H16: =IF(E16=0,"",G16/E16) -> 0.76420765

Sheet Personal
A1: PERSONAL · COSTE LABORAL MENSUAL
A3: Puesto / empleado | B3: Sueldo bruto (€) | C3: % SS empresa | D3: Coste SS (€) | E3: Coste total (€)
A4: Cocinero jefe | B4: 2100 | C4: 0.32 | D4: =IF(B4="","",B4*C4) -> 672 | E4: =IF(B4="","",B4+D4) -> 2772
A5: Segundo de cocina | B5: 1650 | C5: 0.32 | D5: =IF(B5="","",B5*C5) -> 528 | E5: =IF(B5="","",B5+D5) -> 2178
A6: Ayudante de cocina | B6: 1400 | C6: 0.32 | D6: =IF(B6="","",B6*C6) -> 448 | E6: =IF(B6="","",B6+D6) -> 1848
A7: Encargado de sala | B7: 1800 | C7: 0.32 | D7: =IF(B7="","",B7*C7) -> 576 | E7: =IF(B7="","",B7+D7) -> 2376
A8: Camarero/a 1 | B8: 1400 | C8: 0.32 | D8: =IF(B8="","",B8*C8) -> 448 | E8: =IF(B8="","",B8+D8) -> 1848
A9: Camarero/a 2 | B9: 1400 | C9: 0.32 | D9: =IF(B9="","",B9*C9) -> 448 | E9: =IF(B9="","",B9+D9) -> 1848
A10: Camarero/a 3 | B10: 1400 | C10: 0.32 | D10: =IF(B10="","",B10*C10) -> 448 | E10: =IF(B10="","",B10+D10) -> 1848
A11: Extras fin de semana | B11: 800 | C11: 0.32 | D11: =IF(B11="","",B11*C11) -> 256 | E11: =IF(B11="","",B11+D11) -> 1056
A12: TOTAL | B12: =SUM(B4:B11) -> 11950 | D12: =SUM(D4:D11) -> 3824 | E12: =SUM(E4:E11) -> 15774
A14: El 32% de Seguridad Social a cargo de la empresa es una estimación habitual en hostelería; ajústalo con la gestoría.

Sheet Gastos
A1: GASTOS OPERATIVOS MENSUALES
A3: Concepto | B3: Tipo | C3: Importe (€/mes)
A4: Alquiler | B4: Fijo | C4: 3200
A5: Luz | B5: Variable | C5: 950
A6: Gas | B6: Variable | C6: 380
A7: Agua | B7: Fijo | C7: 160
A8: Gestoría | B8: Fijo | C8: 250
A9: Marketing | B9: Fijo | C9: 600
A10: Comisiones delivery (Glovo, etc.) | B10: Variable | C10: 900
A11: Seguros | B11: Fijo | C11: 140
A12: Mantenimiento y reparaciones | B12: Fijo | C12: 200
A13: Música y licencias | B13: Fijo | C13: 60
A14: Menaje y limpieza | B14: Variable | C14: 250
A15: Otros | B15: Variable | C15: 150
A16: TOTAL | C16: =SUM(C4:C15) -> 7240
A17: Total gastos FIJOS | C17: =SUMIF(B4:B15,"Fijo",C4:C15) -> 4610
A18: Total gastos VARIABLES | C18: =SUMIF(B4:B15,"Variable",C4:C15) -> 2630
A20: En Tipo escribe exactamente "Fijo" o "Variable". Fijo = se paga aunque no haya clientes.

Sheet Deuda
A1: DEUDA Y FINANCIACIÓN
A3: Préstamo / acreedor | B3: Capital pendiente (€) | C3: Interés % | D3: Cuota mensual (€) | E3: Meses restantes
A4: Préstamo ICO | B4: 48000 | C4: 0.045 | D4: 890 | E4: 60
A5: Préstamo reforma local | B5: 15000 | C5: 0.062 | D5: 450 | E5: 38
A6: Aplazamiento proveedores | B6: 6000 | C6: 0 | D6: 500 | E6: 12
A11: TOTAL | B11: =SUM(B4:B10) -> 69000 | D11: =SUM(D4:D10) -> 1840
A13: Con esta hoja se ve el endeudamiento total y qué parte de las ventas se va en cuotas (Dashboard).
